Classfile /C:/Users/flyin/Documents/Java/asm-recompiler/src/test/java/com/raptor/test02/TestClass02.class
  Last modified Dec 3, 2020; size 643 bytes
  SHA-256 checksum 3aaa210a46c7d46c5945e86b5cd9cfe80fe6a8d171f7f3a35465f853daa2520f
  Compiled from "TestClass02.java"
public class com.raptor.test02.TestClass02
  minor version: 65535
  major version: 58
  flags: (0x0021) ACC_PUBLIC, ACC_SUPER
  this_class: #7                          // com/raptor/test02/TestClass02
  super_class: #2                         // java/lang/Object
  interfaces: 0, fields: 0, methods: 2, attributes: 3
Constant pool:
   #1 = Methodref          #2.#3          // java/lang/Object."<init>":()V
   #2 = Class              #4             // java/lang/Object
   #3 = NameAndType        #5:#6          // "<init>":()V
   #4 = Utf8               java/lang/Object
   #5 = Utf8               <init>
   #6 = Utf8               ()V
   #7 = Class              #8             // com/raptor/test02/TestClass02
   #8 = Utf8               com/raptor/test02/TestClass02
   #9 = Utf8               Code
  #10 = Utf8               LineNumberTable
  #11 = Utf8               bar
  #12 = Utf8               (Lcom/raptor/test02/TestClass02$C;)V
  #13 = Utf8               Signature
  #14 = Utf8               (Lcom/raptor/test02/TestClass02$C<Lcom/raptor/test02/TestClass02$B;>;)V
  #15 = Utf8               SourceFile
  #16 = Utf8               TestClass02.java
  #17 = Utf8               NestMembers
  #18 = Class              #19            // com/raptor/test02/TestClass02$C
  #19 = Utf8               com/raptor/test02/TestClass02$C
  #20 = Class              #21            // com/raptor/test02/TestClass02$B
  #21 = Utf8               com/raptor/test02/TestClass02$B
  #22 = Class              #23            // com/raptor/test02/TestClass02$B$D
  #23 = Utf8               com/raptor/test02/TestClass02$B$D
  #24 = Class              #25            // com/raptor/test02/TestClass02$A
  #25 = Utf8               com/raptor/test02/TestClass02$A
  #26 = Utf8               InnerClasses
  #27 = Utf8               C
  #28 = Utf8               B
  #29 = Utf8               A
  #30 = Utf8               D
{
  public com.raptor.test02.TestClass02();
    descriptor: ()V
    flags: (0x0001) ACC_PUBLIC
    Code:
      stack=1, locals=1, args_size=1
         0: aload_0
         1: invokespecial #1                  // Method java/lang/Object."<init>":()V
         4: return
      LineNumberTable:
        line 3: 0

  public static void bar(com.raptor.test02.TestClass02$C<com.raptor.test02.TestClass02$B>);
    descriptor: (Lcom/raptor/test02/TestClass02$C;)V
    flags: (0x0009) ACC_PUBLIC, ACC_STATIC
    Code:
      stack=0, locals=1, args_size=1
         0: return
      LineNumberTable:
        line 31: 0
    Signature: #14                          // (Lcom/raptor/test02/TestClass02$C<Lcom/raptor/test02/TestClass02$B;>;)V
}
SourceFile: "TestClass02.java"
NestMembers:
  com/raptor/test02/TestClass02$C
  com/raptor/test02/TestClass02$B
  com/raptor/test02/TestClass02$B$D
  com/raptor/test02/TestClass02$A
InnerClasses:
  public static #27= #18 of #7;           // C=class com/raptor/test02/TestClass02$C of class com/raptor/test02/TestClass02
  public #28= #20 of #7;                  // B=class com/raptor/test02/TestClass02$B of class com/raptor/test02/TestClass02
  public static #29= #24 of #7;           // A=class com/raptor/test02/TestClass02$A of class com/raptor/test02/TestClass02
  public #30= #22 of #20;                 // D=class com/raptor/test02/TestClass02$B$D of class com/raptor/test02/TestClass02$B
