Classfile /C:/Users/flyin/Documents/Java/asm-recompiler/src/test/java/com/raptor/test04/C2.class
  Last modified Dec 3, 2020; size 205 bytes
  SHA-256 checksum b5aa67b5d4846e90c50b68a84325c52610c3ed470b03e31b3ae828fd2c42b636
  Compiled from "TestClass04.java"
class com.raptor.test04.C2
  minor version: 65535
  major version: 58
  flags: (0x0020) ACC_SUPER
  this_class: #7                          // com/raptor/test04/C2
  super_class: #2                         // java/lang/Object
  interfaces: 0, fields: 0, methods: 1, attributes: 1
Constant pool:
   #1 = Methodref          #2.#3          // java/lang/Object."<init>":()V
   #2 = Class              #4             // java/lang/Object
   #3 = NameAndType        #5:#6          // "<init>":()V
   #4 = Utf8               java/lang/Object
   #5 = Utf8               <init>
   #6 = Utf8               ()V
   #7 = Class              #8             // com/raptor/test04/C2
   #8 = Utf8               com/raptor/test04/C2
   #9 = Utf8               Code
  #10 = Utf8               LineNumberTable
  #11 = Utf8               SourceFile
  #12 = Utf8               TestClass04.java
{
  com.raptor.test04.C2();
    descriptor: ()V
    flags: (0x0000)
    Code:
      stack=1, locals=1, args_size=1
         0: aload_0
         1: invokespecial #1                  // Method java/lang/Object."<init>":()V
         4: return
      LineNumberTable:
        line 34: 0
}
SourceFile: "TestClass04.java"
