Classfile /C:/Users/flyin/Documents/Java/asm-recompiler/src/test/java/com/raptor/test02/TestClass02$B.class
  Last modified Dec 3, 2020; size 522 bytes
  SHA-256 checksum 118a8666062deebbb97f98e3267c859d492f3c8e4013d566fdd39f14e8b2fdf8
  Compiled from "TestClass02.java"
public class com.raptor.test02.TestClass02$B<T extends java.lang.Object> extends java.lang.Object
  minor version: 65535
  major version: 58
  flags: (0x0021) ACC_PUBLIC, ACC_SUPER
  this_class: #2                          // com/raptor/test02/TestClass02$B
  super_class: #8                         // java/lang/Object
  interfaces: 0, fields: 1, methods: 1, attributes: 4
Constant pool:
   #1 = Fieldref           #2.#3          // com/raptor/test02/TestClass02$B.this$0:Lcom/raptor/test02/TestClass02;
   #2 = Class              #4             // com/raptor/test02/TestClass02$B
   #3 = NameAndType        #5:#6          // this$0:Lcom/raptor/test02/TestClass02;
   #4 = Utf8               com/raptor/test02/TestClass02$B
   #5 = Utf8               this$0
   #6 = Utf8               Lcom/raptor/test02/TestClass02;
   #7 = Methodref          #8.#9          // java/lang/Object."<init>":()V
   #8 = Class              #10            // java/lang/Object
   #9 = NameAndType        #11:#12        // "<init>":()V
  #10 = Utf8               java/lang/Object
  #11 = Utf8               <init>
  #12 = Utf8               ()V
  #13 = Utf8               (Lcom/raptor/test02/TestClass02;)V
  #14 = Utf8               Code
  #15 = Utf8               LineNumberTable
  #16 = Utf8               Signature
  #17 = Utf8               <T:Ljava/lang/Object;>Ljava/lang/Object;
  #18 = Utf8               SourceFile
  #19 = Utf8               TestClass02.java
  #20 = Utf8               NestHost
  #21 = Class              #22            // com/raptor/test02/TestClass02
  #22 = Utf8               com/raptor/test02/TestClass02
  #23 = Utf8               InnerClasses
  #24 = Utf8               B
  #25 = Class              #26            // com/raptor/test02/TestClass02$B$D
  #26 = Utf8               com/raptor/test02/TestClass02$B$D
  #27 = Utf8               D
{
  final com.raptor.test02.TestClass02 this$0;
    descriptor: Lcom/raptor/test02/TestClass02;
    flags: (0x1010) ACC_FINAL, ACC_SYNTHETIC

  public com.raptor.test02.TestClass02$B(com.raptor.test02.TestClass02);
    descriptor: (Lcom/raptor/test02/TestClass02;)V
    flags: (0x0001) ACC_PUBLIC
    Code:
      stack=2, locals=2, args_size=2
         0: aload_0
         1: aload_1
         2: putfield      #1                  // Field this$0:Lcom/raptor/test02/TestClass02;
         5: aload_0
         6: invokespecial #7                  // Method java/lang/Object."<init>":()V
         9: return
      LineNumberTable:
        line 11: 0
}
Signature: #17                          // <T:Ljava/lang/Object;>Ljava/lang/Object;
SourceFile: "TestClass02.java"
NestHost: class com/raptor/test02/TestClass02
InnerClasses:
  public #24= #2 of #21;                  // B=class com/raptor/test02/TestClass02$B of class com/raptor/test02/TestClass02
  public #27= #25 of #2;                  // D=class com/raptor/test02/TestClass02$B$D of class com/raptor/test02/TestClass02$B
