Classfile /C:/Users/flyin/Documents/Java/asm-recompiler/src/test/java/com/raptor/test02/TestClass02$A.class
  Last modified Dec 3, 2020; size 350 bytes
  SHA-256 checksum e521f71a37511b3195db79630c1b1e2a430149bbf0b145b1599374cd5c31f3d9
  Compiled from "TestClass02.java"
public class com.raptor.test02.TestClass02$A
  minor version: 65535
  major version: 58
  flags: (0x0021) ACC_PUBLIC, ACC_SUPER
  this_class: #7                          // com/raptor/test02/TestClass02$A
  super_class: #2                         // java/lang/Object
  interfaces: 0, fields: 0, methods: 2, attributes: 3
Constant pool:
   #1 = Methodref          #2.#3          // java/lang/Object."<init>":()V
   #2 = Class              #4             // java/lang/Object
   #3 = NameAndType        #5:#6          // "<init>":()V
   #4 = Utf8               java/lang/Object
   #5 = Utf8               <init>
   #6 = Utf8               ()V
   #7 = Class              #8             // com/raptor/test02/TestClass02$A
   #8 = Utf8               com/raptor/test02/TestClass02$A
   #9 = Utf8               Code
  #10 = Utf8               LineNumberTable
  #11 = Utf8               foo
  #12 = Utf8               SourceFile
  #13 = Utf8               TestClass02.java
  #14 = Utf8               NestHost
  #15 = Class              #16            // com/raptor/test02/TestClass02
  #16 = Utf8               com/raptor/test02/TestClass02
  #17 = Utf8               InnerClasses
  #18 = Utf8               A
{
  public com.raptor.test02.TestClass02$A();
    descriptor: ()V
    flags: (0x0001) ACC_PUBLIC
    Code:
      stack=1, locals=1, args_size=1
         0: aload_0
         1: invokespecial #1                  // Method java/lang/Object."<init>":()V
         4: return
      LineNumberTable:
        line 5: 0

  public void foo();
    descriptor: ()V
    flags: (0x0001) ACC_PUBLIC
    Code:
      stack=0, locals=1, args_size=1
         0: return
      LineNumberTable:
        line 7: 0
}
SourceFile: "TestClass02.java"
NestHost: class com/raptor/test02/TestClass02
InnerClasses:
  public static #18= #7 of #15;           // A=class com/raptor/test02/TestClass02$A of class com/raptor/test02/TestClass02
