Classfile /C:/Users/flyin/Documents/Java/asm-recompiler/src/test/java/com/raptor/test01/Magazine.class
  Last modified Dec 2, 2020; size 1733 bytes
  SHA-256 checksum 5814210c9db62ecc13b492dcf6e9e8dd0e6c6be46cbc076909698422372f0ade
  Compiled from "TestClass01.java"
final class com.raptor.test01.Magazine extends java.lang.Record implements com.raptor.test01.Literature
  minor version: 65535
  major version: 58
  flags: (0x0030) ACC_FINAL, ACC_SUPER
  this_class: #34                         // com/raptor/test01/Magazine
  super_class: #2                         // java/lang/Record
  interfaces: 1, fields: 2, methods: 6, attributes: 4
Constant pool:
   #1 = Methodref          #2.#3          // java/lang/Record."<init>":()V
   #2 = Class              #4             // java/lang/Record
   #3 = NameAndType        #5:#6          // "<init>":()V
   #4 = Utf8               java/lang/Record
   #5 = Utf8               <init>
   #6 = Utf8               ()V
   #7 = Class              #8             // java/lang/NullPointerException
   #8 = Utf8               java/lang/NullPointerException
   #9 = String             #10            // name
  #10 = Utf8               name
  #11 = Methodref          #7.#12         // java/lang/NullPointerException."<init>":(Ljava/lang/String;)V
  #12 = NameAndType        #5:#13         // "<init>":(Ljava/lang/String;)V
  #13 = Utf8               (Ljava/lang/String;)V
  #14 = String             #15            // edition
  #15 = Utf8               edition
  #16 = Methodref          #17.#18        // java/lang/String.strip:()Ljava/lang/String;
  #17 = Class              #19            // java/lang/String
  #18 = NameAndType        #20:#21        // strip:()Ljava/lang/String;
  #19 = Utf8               java/lang/String
  #20 = Utf8               strip
  #21 = Utf8               ()Ljava/lang/String;
  #22 = Methodref          #17.#23        // java/lang/String.isEmpty:()Z
  #23 = NameAndType        #24:#25        // isEmpty:()Z
  #24 = Utf8               isEmpty
  #25 = Utf8               ()Z
  #26 = Class              #27            // java/lang/IllegalArgumentException
  #27 = Utf8               java/lang/IllegalArgumentException
  #28 = String             #29            // name may not be blank
  #29 = Utf8               name may not be blank
  #30 = Methodref          #26.#12        // java/lang/IllegalArgumentException."<init>":(Ljava/lang/String;)V
  #31 = String             #32            // edition may not be blank
  #32 = Utf8               edition may not be blank
  #33 = Fieldref           #34.#35        // com/raptor/test01/Magazine.name:Ljava/lang/String;
  #34 = Class              #36            // com/raptor/test01/Magazine
  #35 = NameAndType        #10:#37        // name:Ljava/lang/String;
  #36 = Utf8               com/raptor/test01/Magazine
  #37 = Utf8               Ljava/lang/String;
  #38 = Fieldref           #34.#39        // com/raptor/test01/Magazine.edition:Ljava/lang/String;
  #39 = NameAndType        #15:#37        // edition:Ljava/lang/String;
  #40 = Fieldref           #34.#35        // com/raptor/test01/Magazine.name:Ljava/lang/String;
  #41 = Fieldref           #34.#39        // com/raptor/test01/Magazine.edition:Ljava/lang/String;
  #42 = InvokeDynamic      #0:#43         // #0:toString:(Lcom/raptor/test01/Magazine;)Ljava/lang/String;
  #43 = NameAndType        #44:#45        // toString:(Lcom/raptor/test01/Magazine;)Ljava/lang/String;
  #44 = Utf8               toString
  #45 = Utf8               (Lcom/raptor/test01/Magazine;)Ljava/lang/String;
  #46 = InvokeDynamic      #0:#47         // #0:hashCode:(Lcom/raptor/test01/Magazine;)I
  #47 = NameAndType        #48:#49        // hashCode:(Lcom/raptor/test01/Magazine;)I
  #48 = Utf8               hashCode
  #49 = Utf8               (Lcom/raptor/test01/Magazine;)I
  #50 = InvokeDynamic      #0:#51         // #0:equals:(Lcom/raptor/test01/Magazine;Ljava/lang/Object;)Z
  #51 = NameAndType        #52:#53        // equals:(Lcom/raptor/test01/Magazine;Ljava/lang/Object;)Z
  #52 = Utf8               equals
  #53 = Utf8               (Lcom/raptor/test01/Magazine;Ljava/lang/Object;)Z
  #54 = Class              #55            // com/raptor/test01/Literature
  #55 = Utf8               com/raptor/test01/Literature
  #56 = Utf8               (Ljava/lang/String;Ljava/lang/String;)V
  #57 = Utf8               Code
  #58 = Utf8               LineNumberTable
  #59 = Utf8               StackMapTable
  #60 = Utf8               MethodParameters
  #61 = Utf8               ()I
  #62 = Utf8               (Ljava/lang/Object;)Z
  #63 = Utf8               SourceFile
  #64 = Utf8               TestClass01.java
  #65 = Utf8               Record
  #66 = Utf8               BootstrapMethods
  #67 = MethodHandle       6:#68          // REF_invokeStatic java/lang/runtime/ObjectMethods.bootstrap:(Ljava/lang/invoke/MethodHandles$Lookup;Ljava/lang/String;Ljava/lang/invoke/TypeDescriptor;Ljava/lang/Class;Ljava/lang/String;[Ljava/lang/invoke/MethodHandle;)Ljava/lang/Object;
  #68 = Methodref          #69.#70        // java/lang/runtime/ObjectMethods.bootstrap:(Ljava/lang/invoke/MethodHandles$Lookup;Ljava/lang/String;Ljava/lang/invoke/TypeDescriptor;Ljava/lang/Class;Ljava/lang/String;[Ljava/lang/invoke/MethodHandle;)Ljava/lang/Object;
  #69 = Class              #71            // java/lang/runtime/ObjectMethods
  #70 = NameAndType        #72:#73        // bootstrap:(Ljava/lang/invoke/MethodHandles$Lookup;Ljava/lang/String;Ljava/lang/invoke/TypeDescriptor;Ljava/lang/Class;Ljava/lang/String;[Ljava/lang/invoke/MethodHandle;)Ljava/lang/Object;
  #71 = Utf8               java/lang/runtime/ObjectMethods
  #72 = Utf8               bootstrap
  #73 = Utf8               (Ljava/lang/invoke/MethodHandles$Lookup;Ljava/lang/String;Ljava/lang/invoke/TypeDescriptor;Ljava/lang/Class;Ljava/lang/String;[Ljava/lang/invoke/MethodHandle;)Ljava/lang/Object;
  #74 = String             #75            // name;edition
  #75 = Utf8               name;edition
  #76 = MethodHandle       1:#33          // REF_getField com/raptor/test01/Magazine.name:Ljava/lang/String;
  #77 = MethodHandle       1:#38          // REF_getField com/raptor/test01/Magazine.edition:Ljava/lang/String;
  #78 = Utf8               InnerClasses
  #79 = Class              #80            // java/lang/invoke/MethodHandles$Lookup
  #80 = Utf8               java/lang/invoke/MethodHandles$Lookup
  #81 = Class              #82            // java/lang/invoke/MethodHandles
  #82 = Utf8               java/lang/invoke/MethodHandles
  #83 = Utf8               Lookup
{
  private final java.lang.String name;
    descriptor: Ljava/lang/String;
    flags: (0x0012) ACC_PRIVATE, ACC_FINAL

  private final java.lang.String edition;
    descriptor: Ljava/lang/String;
    flags: (0x0012) ACC_PRIVATE, ACC_FINAL

  public com.raptor.test01.Magazine(java.lang.String, java.lang.String);
    descriptor: (Ljava/lang/String;Ljava/lang/String;)V
    flags: (0x0001) ACC_PUBLIC
    Code:
      stack=3, locals=3, args_size=3
         0: aload_0
         1: invokespecial #1                  // Method java/lang/Record."<init>":()V
         4: aload_1
         5: ifnonnull     18
         8: new           #7                  // class java/lang/NullPointerException
        11: dup
        12: ldc           #9                  // String name
        14: invokespecial #11                 // Method java/lang/NullPointerException."<init>":(Ljava/lang/String;)V
        17: athrow
        18: aload_2
        19: ifnonnull     32
        22: new           #7                  // class java/lang/NullPointerException
        25: dup
        26: ldc           #14                 // String edition
        28: invokespecial #11                 // Method java/lang/NullPointerException."<init>":(Ljava/lang/String;)V
        31: athrow
        32: aload_1
        33: invokevirtual #16                 // Method java/lang/String.strip:()Ljava/lang/String;
        36: dup
        37: astore_1
        38: invokevirtual #22                 // Method java/lang/String.isEmpty:()Z
        41: ifeq          54
        44: new           #26                 // class java/lang/IllegalArgumentException
        47: dup
        48: ldc           #28                 // String name may not be blank
        50: invokespecial #30                 // Method java/lang/IllegalArgumentException."<init>":(Ljava/lang/String;)V
        53: athrow
        54: aload_2
        55: invokevirtual #16                 // Method java/lang/String.strip:()Ljava/lang/String;
        58: dup
        59: astore_2
        60: invokevirtual #22                 // Method java/lang/String.isEmpty:()Z
        63: ifeq          76
        66: new           #26                 // class java/lang/IllegalArgumentException
        69: dup
        70: ldc           #31                 // String edition may not be blank
        72: invokespecial #30                 // Method java/lang/IllegalArgumentException."<init>":(Ljava/lang/String;)V
        75: athrow
        76: aload_0
        77: aload_1
        78: putfield      #33                 // Field name:Ljava/lang/String;
        81: aload_0
        82: aload_2
        83: putfield      #38                 // Field edition:Ljava/lang/String;
        86: return
      LineNumberTable:
        line 127: 0
        line 128: 4
        line 129: 18
        line 130: 32
        line 131: 54
        line 133: 76
        line 134: 81
        line 135: 86
      StackMapTable: number_of_entries = 4
        frame_type = 255 /* full_frame */
          offset_delta = 18
          locals = [ class com/raptor/test01/Magazine, class java/lang/String, class java/lang/String ]
          stack = []
        frame_type = 13 /* same */
        frame_type = 21 /* same */
        frame_type = 21 /* same */
    MethodParameters:
      Name                           Flags
      name
      edition

  public java.lang.String toString();
    descriptor: ()Ljava/lang/String;
    flags: (0x0001) ACC_PUBLIC
    Code:
      stack=1, locals=1, args_size=1
         0: aload_0
         1: invokedynamic #42,  0             // InvokeDynamic #0:toString:(Lcom/raptor/test01/Magazine;)Ljava/lang/String;
         6: areturn
      LineNumberTable:
        line 125: 0

  public final int hashCode();
    descriptor: ()I
    flags: (0x0011) ACC_PUBLIC, ACC_FINAL
    Code:
      stack=1, locals=1, args_size=1
         0: aload_0
         1: invokedynamic #46,  0             // InvokeDynamic #0:hashCode:(Lcom/raptor/test01/Magazine;)I
         6: ireturn
      LineNumberTable:
        line 125: 0

  public final boolean equals(java.lang.Object);
    descriptor: (Ljava/lang/Object;)Z
    flags: (0x0011) ACC_PUBLIC, ACC_FINAL
    Code:
      stack=2, locals=2, args_size=2
         0: aload_0
         1: aload_1
         2: invokedynamic #50,  0             // InvokeDynamic #0:equals:(Lcom/raptor/test01/Magazine;Ljava/lang/Object;)Z
         7: ireturn
      LineNumberTable:
        line 125: 0

  public java.lang.String name();
    descriptor: ()Ljava/lang/String;
    flags: (0x0001) ACC_PUBLIC
    Code:
      stack=1, locals=1, args_size=1
         0: aload_0
         1: getfield      #40                 // Field name:Ljava/lang/String;
         4: areturn
      LineNumberTable:
        line 125: 0

  public java.lang.String edition();
    descriptor: ()Ljava/lang/String;
    flags: (0x0001) ACC_PUBLIC
    Code:
      stack=1, locals=1, args_size=1
         0: aload_0
         1: getfield      #41                 // Field edition:Ljava/lang/String;
         4: areturn
      LineNumberTable:
        line 125: 0
}
SourceFile: "TestClass01.java"
Record:
  java.lang.String name;
    descriptor: Ljava/lang/String;

  java.lang.String edition;
    descriptor: Ljava/lang/String;

BootstrapMethods:
  0: #67 REF_invokeStatic java/lang/runtime/ObjectMethods.bootstrap:(Ljava/lang/invoke/MethodHandles$Lookup;Ljava/lang/String;Ljava/lang/invoke/TypeDescriptor;Ljava/lang/Class;Ljava/lang/String;[Ljava/lang/invoke/MethodHandle;)Ljava/lang/Object;
    Method arguments:
      #34 com/raptor/test01/Magazine
      #74 name;edition
      #76 REF_getField com/raptor/test01/Magazine.name:Ljava/lang/String;
      #77 REF_getField com/raptor/test01/Magazine.edition:Ljava/lang/String;
InnerClasses:
  public static final #83= #79 of #81;    // Lookup=class java/lang/invoke/MethodHandles$Lookup of class java/lang/invoke/MethodHandles
