Classfile /C:/Users/flyin/Documents/Java/asm-recompiler/src/test/java/com/raptor/test01/WebArticle.class
  Last modified Dec 2, 2020; size 2747 bytes
  SHA-256 checksum f996922cbe8cd0c6d9eea8537639c09e5fdd03e06e2fa8f4d60740315c2b8e07
  Compiled from "TestClass01.java"
final class com.raptor.test01.WebArticle extends com.raptor.test01.Article implements com.raptor.test01.Literature, com.raptor.test01.ContainedLiterature<com.raptor.test01.Website>
  minor version: 65535
  major version: 58
  flags: (0x0030) ACC_FINAL, ACC_SUPER
  this_class: #49                         // com/raptor/test01/WebArticle
  super_class: #2                         // com/raptor/test01/Article
  interfaces: 2, fields: 2, methods: 8, attributes: 4
Constant pool:
    #1 = Methodref          #2.#3         // com/raptor/test01/Article."<init>":(Ljava/lang/String;Ljava/lang/String;)V
    #2 = Class              #4            // com/raptor/test01/Article
    #3 = NameAndType        #5:#6         // "<init>":(Ljava/lang/String;Ljava/lang/String;)V
    #4 = Utf8               com/raptor/test01/Article
    #5 = Utf8               <init>
    #6 = Utf8               (Ljava/lang/String;Ljava/lang/String;)V
    #7 = Class              #8            // java/lang/NullPointerException
    #8 = Utf8               java/lang/NullPointerException
    #9 = String             #10           // website
   #10 = Utf8               website
   #11 = Methodref          #7.#12        // java/lang/NullPointerException."<init>":(Ljava/lang/String;)V
   #12 = NameAndType        #5:#13        // "<init>":(Ljava/lang/String;)V
   #13 = Utf8               (Ljava/lang/String;)V
   #14 = String             #15           // articleURL
   #15 = Utf8               articleURL
   #16 = Methodref          #17.#18       // com/raptor/test01/Website.homepageURL:()Ljava/net/URL;
   #17 = Class              #19           // com/raptor/test01/Website
   #18 = NameAndType        #20:#21       // homepageURL:()Ljava/net/URL;
   #19 = Utf8               com/raptor/test01/Website
   #20 = Utf8               homepageURL
   #21 = Utf8               ()Ljava/net/URL;
   #22 = Methodref          #23.#24       // java/net/URL.getHost:()Ljava/lang/String;
   #23 = Class              #25           // java/net/URL
   #24 = NameAndType        #26:#27       // getHost:()Ljava/lang/String;
   #25 = Utf8               java/net/URL
   #26 = Utf8               getHost
   #27 = Utf8               ()Ljava/lang/String;
   #28 = String             #29           // www.
   #29 = Utf8               www.
   #30 = Methodref          #31.#32       // java/lang/String.startsWith:(Ljava/lang/String;)Z
   #31 = Class              #33           // java/lang/String
   #32 = NameAndType        #34:#35       // startsWith:(Ljava/lang/String;)Z
   #33 = Utf8               java/lang/String
   #34 = Utf8               startsWith
   #35 = Utf8               (Ljava/lang/String;)Z
   #36 = Methodref          #31.#37       // java/lang/String.substring:(I)Ljava/lang/String;
   #37 = NameAndType        #38:#39       // substring:(I)Ljava/lang/String;
   #38 = Utf8               substring
   #39 = Utf8               (I)Ljava/lang/String;
   #40 = Methodref          #31.#41       // java/lang/String.endsWith:(Ljava/lang/String;)Z
   #41 = NameAndType        #42:#35       // endsWith:(Ljava/lang/String;)Z
   #42 = Utf8               endsWith
   #43 = Class              #44           // java/lang/IllegalArgumentException
   #44 = Utf8               java/lang/IllegalArgumentException
   #45 = String             #46           // articleURL is not on the given website
   #46 = Utf8               articleURL is not on the given website
   #47 = Methodref          #43.#12       // java/lang/IllegalArgumentException."<init>":(Ljava/lang/String;)V
   #48 = Fieldref           #49.#50       // com/raptor/test01/WebArticle.website:Lcom/raptor/test01/Website;
   #49 = Class              #51           // com/raptor/test01/WebArticle
   #50 = NameAndType        #10:#52       // website:Lcom/raptor/test01/Website;
   #51 = Utf8               com/raptor/test01/WebArticle
   #52 = Utf8               Lcom/raptor/test01/Website;
   #53 = Fieldref           #49.#54       // com/raptor/test01/WebArticle.articleURL:Ljava/net/URL;
   #54 = NameAndType        #15:#55       // articleURL:Ljava/net/URL;
   #55 = Utf8               Ljava/net/URL;
   #56 = Class              #57           // java/lang/Object
   #57 = Utf8               java/lang/Object
   #58 = Fieldref           #49.#59       // com/raptor/test01/WebArticle.name:Ljava/lang/String;
   #59 = NameAndType        #60:#61       // name:Ljava/lang/String;
   #60 = Utf8               name
   #61 = Utf8               Ljava/lang/String;
   #62 = Fieldref           #49.#63       // com/raptor/test01/WebArticle.author:Ljava/lang/String;
   #63 = NameAndType        #64:#61       // author:Ljava/lang/String;
   #64 = Utf8               author
   #65 = Methodref          #66.#67       // java/util/Objects.hash:([Ljava/lang/Object;)I
   #66 = Class              #68           // java/util/Objects
   #67 = NameAndType        #69:#70       // hash:([Ljava/lang/Object;)I
   #68 = Utf8               java/util/Objects
   #69 = Utf8               hash
   #70 = Utf8               ([Ljava/lang/Object;)I
   #71 = Methodref          #17.#72       // com/raptor/test01/Website.equals:(Ljava/lang/Object;)Z
   #72 = NameAndType        #73:#74       // equals:(Ljava/lang/Object;)Z
   #73 = Utf8               equals
   #74 = Utf8               (Ljava/lang/Object;)Z
   #75 = Methodref          #23.#72       // java/net/URL.equals:(Ljava/lang/Object;)Z
   #76 = Methodref          #31.#72       // java/lang/String.equals:(Ljava/lang/Object;)Z
   #77 = Methodref          #56.#78       // java/lang/Object.getClass:()Ljava/lang/Class;
   #78 = NameAndType        #79:#80       // getClass:()Ljava/lang/Class;
   #79 = Utf8               getClass
   #80 = Utf8               ()Ljava/lang/Class;
   #81 = Methodref          #82.#83       // java/lang/Class.getSimpleName:()Ljava/lang/String;
   #82 = Class              #84           // java/lang/Class
   #83 = NameAndType        #85:#27       // getSimpleName:()Ljava/lang/String;
   #84 = Utf8               java/lang/Class
   #85 = Utf8               getSimpleName
   #86 = InvokeDynamic      #0:#87        // #0:makeConcatWithConstants:(Ljava/lang/String;Lcom/raptor/test01/Website;Ljava/net/URL;Ljava/lang/String;Ljava/lang/String;)Ljava/lang/String;
   #87 = NameAndType        #88:#89       // makeConcatWithConstants:(Ljava/lang/String;Lcom/raptor/test01/Website;Ljava/net/URL;Ljava/lang/String;Ljava/lang/String;)Ljava/lang/String;
   #88 = Utf8               makeConcatWithConstants
   #89 = Utf8               (Ljava/lang/String;Lcom/raptor/test01/Website;Ljava/net/URL;Ljava/lang/String;Ljava/lang/String;)Ljava/lang/String;
   #90 = Methodref          #49.#91       // com/raptor/test01/WebArticle.getContainer:()Lcom/raptor/test01/Website;
   #91 = NameAndType        #92:#93       // getContainer:()Lcom/raptor/test01/Website;
   #92 = Utf8               getContainer
   #93 = Utf8               ()Lcom/raptor/test01/Website;
   #94 = Class              #95           // com/raptor/test01/Literature
   #95 = Utf8               com/raptor/test01/Literature
   #96 = Class              #97           // com/raptor/test01/ContainedLiterature
   #97 = Utf8               com/raptor/test01/ContainedLiterature
   #98 = Utf8               (Lcom/raptor/test01/Website;Ljava/net/URL;Ljava/lang/String;Ljava/lang/String;)V
   #99 = Utf8               Code
  #100 = Utf8               LineNumberTable
  #101 = Utf8               StackMapTable
  #102 = Utf8               hashCode
  #103 = Utf8               ()I
  #104 = Utf8               toString
  #105 = Utf8               ()Lcom/raptor/test01/Literature;
  #106 = Utf8               Signature
  #107 = Utf8               Lcom/raptor/test01/Article;Lcom/raptor/test01/Literature;Lcom/raptor/test01/ContainedLiterature<Lcom/raptor/test01/Website;>;
  #108 = Utf8               SourceFile
  #109 = Utf8               TestClass01.java
  #110 = Utf8               BootstrapMethods
  #111 = MethodHandle       6:#112        // REF_invokeStatic java/lang/invoke/StringConcatFactory.makeConcatWithConstants:(Ljava/lang/invoke/MethodHandles$Lookup;Ljava/lang/String;Ljava/lang/invoke/MethodType;Ljava/lang/String;[Ljava/lang/Object;)Ljava/lang/invoke/CallSite;
  #112 = Methodref          #113.#114     // java/lang/invoke/StringConcatFactory.makeConcatWithConstants:(Ljava/lang/invoke/MethodHandles$Lookup;Ljava/lang/String;Ljava/lang/invoke/MethodType;Ljava/lang/String;[Ljava/lang/Object;)Ljava/lang/invoke/CallSite;
  #113 = Class              #115          // java/lang/invoke/StringConcatFactory
  #114 = NameAndType        #88:#116      // makeConcatWithConstants:(Ljava/lang/invoke/MethodHandles$Lookup;Ljava/lang/String;Ljava/lang/invoke/MethodType;Ljava/lang/String;[Ljava/lang/Object;)Ljava/lang/invoke/CallSite;
  #115 = Utf8               java/lang/invoke/StringConcatFactory
  #116 = Utf8               (Ljava/lang/invoke/MethodHandles$Lookup;Ljava/lang/String;Ljava/lang/invoke/MethodType;Ljava/lang/String;[Ljava/lang/Object;)Ljava/lang/invoke/CallSite;
  #117 = String             #118          // \u0001[website=\u0001, articleURL=\u0001, name=\u0001, author=\u0001]
  #118 = Utf8               \u0001[website=\u0001, articleURL=\u0001, name=\u0001, author=\u0001]
  #119 = Utf8               InnerClasses
  #120 = Class              #121          // java/lang/invoke/MethodHandles$Lookup
  #121 = Utf8               java/lang/invoke/MethodHandles$Lookup
  #122 = Class              #123          // java/lang/invoke/MethodHandles
  #123 = Utf8               java/lang/invoke/MethodHandles
  #124 = Utf8               Lookup
{
  private final com.raptor.test01.Website website;
    descriptor: Lcom/raptor/test01/Website;
    flags: (0x0012) ACC_PRIVATE, ACC_FINAL

  private final java.net.URL articleURL;
    descriptor: Ljava/net/URL;
    flags: (0x0012) ACC_PRIVATE, ACC_FINAL

  public com.raptor.test01.WebArticle(com.raptor.test01.Website, java.net.URL, java.lang.String, java.lang.String);
    descriptor: (Lcom/raptor/test01/Website;Ljava/net/URL;Ljava/lang/String;Ljava/lang/String;)V
    flags: (0x0001) ACC_PUBLIC
    Code:
      stack=3, locals=6, args_size=5
         0: aload_0
         1: aload_3
         2: aload         4
         4: invokespecial #1                  // Method com/raptor/test01/Article."<init>":(Ljava/lang/String;Ljava/lang/String;)V
         7: aload_1
         8: ifnonnull     21
        11: new           #7                  // class java/lang/NullPointerException
        14: dup
        15: ldc           #9                  // String website
        17: invokespecial #11                 // Method java/lang/NullPointerException."<init>":(Ljava/lang/String;)V
        20: athrow
        21: aload_2
        22: ifnonnull     35
        25: new           #7                  // class java/lang/NullPointerException
        28: dup
        29: ldc           #14                 // String articleURL
        31: invokespecial #11                 // Method java/lang/NullPointerException."<init>":(Ljava/lang/String;)V
        34: athrow
        35: aload_1
        36: invokevirtual #16                 // Method com/raptor/test01/Website.homepageURL:()Ljava/net/URL;
        39: invokevirtual #22                 // Method java/net/URL.getHost:()Ljava/lang/String;
        42: astore        5
        44: aload         5
        46: ldc           #28                 // String www.
        48: invokevirtual #30                 // Method java/lang/String.startsWith:(Ljava/lang/String;)Z
        51: ifeq          62
        54: aload         5
        56: iconst_4
        57: invokevirtual #36                 // Method java/lang/String.substring:(I)Ljava/lang/String;
        60: astore        5
        62: aload_2
        63: invokevirtual #22                 // Method java/net/URL.getHost:()Ljava/lang/String;
        66: aload         5
        68: invokevirtual #40                 // Method java/lang/String.endsWith:(Ljava/lang/String;)Z
        71: ifne          84
        74: new           #43                 // class java/lang/IllegalArgumentException
        77: dup
        78: ldc           #45                 // String articleURL is not on the given website
        80: invokespecial #47                 // Method java/lang/IllegalArgumentException."<init>":(Ljava/lang/String;)V
        83: athrow
        84: aload_0
        85: aload_1
        86: putfield      #48                 // Field website:Lcom/raptor/test01/Website;
        89: aload_0
        90: aload_2
        91: putfield      #53                 // Field articleURL:Ljava/net/URL;
        94: return
      LineNumberTable:
        line 208: 0
        line 209: 7
        line 210: 21
        line 212: 35
        line 213: 44
        line 214: 54
        line 217: 62
        line 219: 84
        line 220: 89
        line 221: 94
      StackMapTable: number_of_entries = 4
        frame_type = 255 /* full_frame */
          offset_delta = 21
          locals = [ class com/raptor/test01/WebArticle, class com/raptor/test01/Website, class java/net/URL, class java/lang/String, class java/lang/String ]
          stack = []
        frame_type = 13 /* same */
        frame_type = 252 /* append */
          offset_delta = 26
          locals = [ class java/lang/String ]
        frame_type = 21 /* same */

  public final com.raptor.test01.Website website();
    descriptor: ()Lcom/raptor/test01/Website;
    flags: (0x0011) ACC_PUBLIC, ACC_FINAL
    Code:
      stack=1, locals=1, args_size=1
         0: aload_0
         1: getfield      #48                 // Field website:Lcom/raptor/test01/Website;
         4: areturn
      LineNumberTable:
        line 223: 0

  public final java.net.URL articleURL();
    descriptor: ()Ljava/net/URL;
    flags: (0x0011) ACC_PUBLIC, ACC_FINAL
    Code:
      stack=1, locals=1, args_size=1
         0: aload_0
         1: getfield      #53                 // Field articleURL:Ljava/net/URL;
         4: areturn
      LineNumberTable:
        line 225: 0

  public final com.raptor.test01.Website getContainer();
    descriptor: ()Lcom/raptor/test01/Website;
    flags: (0x0011) ACC_PUBLIC, ACC_FINAL
    Code:
      stack=1, locals=1, args_size=1
         0: aload_0
         1: getfield      #48                 // Field website:Lcom/raptor/test01/Website;
         4: areturn
      LineNumberTable:
        line 228: 0

  public int hashCode();
    descriptor: ()I
    flags: (0x0001) ACC_PUBLIC
    Code:
      stack=4, locals=1, args_size=1
         0: iconst_4
         1: anewarray     #56                 // class java/lang/Object
         4: dup
         5: iconst_0
         6: aload_0
         7: getfield      #48                 // Field website:Lcom/raptor/test01/Website;
        10: aastore
        11: dup
        12: iconst_1
        13: aload_0
        14: getfield      #53                 // Field articleURL:Ljava/net/URL;
        17: aastore
        18: dup
        19: iconst_2
        20: aload_0
        21: getfield      #58                 // Field name:Ljava/lang/String;
        24: aastore
        25: dup
        26: iconst_3
        27: aload_0
        28: getfield      #62                 // Field author:Ljava/lang/String;
        31: aastore
        32: invokestatic  #65                 // Method java/util/Objects.hash:([Ljava/lang/Object;)I
        35: ireturn
      LineNumberTable:
        line 232: 0

  public boolean equals(java.lang.Object);
    descriptor: (Ljava/lang/Object;)Z
    flags: (0x0001) ACC_PUBLIC
    Code:
      stack=2, locals=4, args_size=2
         0: aload_0
         1: aload_1
         2: if_acmpne     7
         5: iconst_1
         6: ireturn
         7: aload_1
         8: astore_3
         9: aload_3
        10: instanceof    #49                 // class com/raptor/test01/WebArticle
        13: ifeq          29
        16: aload_3
        17: checkcast     #49                 // class com/raptor/test01/WebArticle
        20: dup
        21: astore_2
        22: aload_3
        23: checkcast     #49                 // class com/raptor/test01/WebArticle
        26: if_acmpeq     31
        29: iconst_0
        30: ireturn
        31: aload_0
        32: getfield      #48                 // Field website:Lcom/raptor/test01/Website;
        35: aload_2
        36: getfield      #48                 // Field website:Lcom/raptor/test01/Website;
        39: invokevirtual #71                 // Method com/raptor/test01/Website.equals:(Ljava/lang/Object;)Z
        42: ifeq          91
        45: aload_0
        46: getfield      #53                 // Field articleURL:Ljava/net/URL;
        49: aload_2
        50: getfield      #53                 // Field articleURL:Ljava/net/URL;
        53: invokevirtual #75                 // Method java/net/URL.equals:(Ljava/lang/Object;)Z
        56: ifeq          91
        59: aload_0
        60: getfield      #58                 // Field name:Ljava/lang/String;
        63: aload_2
        64: getfield      #58                 // Field name:Ljava/lang/String;
        67: invokevirtual #76                 // Method java/lang/String.equals:(Ljava/lang/Object;)Z
        70: ifeq          91
        73: aload_0
        74: getfield      #62                 // Field author:Ljava/lang/String;
        77: aload_2
        78: getfield      #62                 // Field author:Ljava/lang/String;
        81: invokevirtual #76                 // Method java/lang/String.equals:(Ljava/lang/Object;)Z
        84: ifeq          91
        87: iconst_1
        88: goto          92
        91: iconst_0
        92: ireturn
      LineNumberTable:
        line 237: 0
        line 238: 7
        line 239: 31
      StackMapTable: number_of_entries = 5
        frame_type = 7 /* same */
        frame_type = 21 /* same */
        frame_type = 252 /* append */
          offset_delta = 1
          locals = [ class com/raptor/test01/WebArticle ]
        frame_type = 59 /* same */
        frame_type = 64 /* same_locals_1_stack_item */
          stack = [ int ]

  public java.lang.String toString();
    descriptor: ()Ljava/lang/String;
    flags: (0x0001) ACC_PUBLIC
    Code:
      stack=5, locals=1, args_size=1
         0: aload_0
         1: invokevirtual #77                 // Method java/lang/Object.getClass:()Ljava/lang/Class;
         4: invokevirtual #81                 // Method java/lang/Class.getSimpleName:()Ljava/lang/String;
         7: aload_0
         8: getfield      #48                 // Field website:Lcom/raptor/test01/Website;
        11: aload_0
        12: getfield      #53                 // Field articleURL:Ljava/net/URL;
        15: aload_0
        16: getfield      #58                 // Field name:Ljava/lang/String;
        19: aload_0
        20: getfield      #62                 // Field author:Ljava/lang/String;
        23: invokedynamic #86,  0             // InvokeDynamic #0:makeConcatWithConstants:(Ljava/lang/String;Lcom/raptor/test01/Website;Ljava/net/URL;Ljava/lang/String;Ljava/lang/String;)Ljava/lang/String;
        28: areturn
      LineNumberTable:
        line 244: 0

  public com.raptor.test01.Literature getContainer();
    descriptor: ()Lcom/raptor/test01/Literature;
    flags: (0x1041) ACC_PUBLIC, ACC_BRIDGE, ACC_SYNTHETIC
    Code:
      stack=1, locals=1, args_size=1
         0: aload_0
         1: invokevirtual #90                 // Method getContainer:()Lcom/raptor/test01/Website;
         4: areturn
      LineNumberTable:
        line 203: 0
}
Signature: #107                         // Lcom/raptor/test01/Article;Lcom/raptor/test01/Literature;Lcom/raptor/test01/ContainedLiterature<Lcom/raptor/test01/Website;>;
SourceFile: "TestClass01.java"
BootstrapMethods:
  0: #111 REF_invokeStatic java/lang/invoke/StringConcatFactory.makeConcatWithConstants:(Ljava/lang/invoke/MethodHandles$Lookup;Ljava/lang/String;Ljava/lang/invoke/MethodType;Ljava/lang/String;[Ljava/lang/Object;)Ljava/lang/invoke/CallSite;
    Method arguments:
      #117 \u0001[website=\u0001, articleURL=\u0001, name=\u0001, author=\u0001]
InnerClasses:
  public static final #124= #120 of #122; // Lookup=class java/lang/invoke/MethodHandles$Lookup of class java/lang/invoke/MethodHandles
